{
  "name": {
    "en": "Shelly 3EM",
    "nl": "Shelly 3EM"
  },
  "images": {
    "large": "./assets/drivers/shelly3em/images/large.jpg",
    "small": "./assets/drivers/shelly3em/images/small.jpg"
  },
  "class": "socket",
  "$extends": [
    "defaults_cloud"
  ],
  "capabilities": [
    "onoff",
    "measure_power",
    "meter_power_factor",
    "measure_current",
    "measure_voltage",
    "meter_power",
    "meter_power_returned",
    "rssi"
  ],
  "pair": [
    {
      "id": "cloud_pairing_form",
      "$template": "cloud_pairing_form"
    },
    {
      "id": "add_device"
    }
  ],
  "energy": {
    "cumulative": true
  }
}
